terminaltranslator.py
terminaltranslator-1.0.dist-info/DESCRIPTION.rst
terminaltranslator-1.0.dist-info/METADATA
terminaltranslator-1.0.dist-info/RECORD
terminaltranslator-1.0.dist-info/WHEEL
terminaltranslator-1.0.dist-info/entry_points.txt
terminaltranslator-1.0.dist-info/metadata.json
terminaltranslator-1.0.dist-info/top_level.txt
