Metadata-Version: 2.0
Name: terminaltranslator
Version: 1.0
Summary: Linux terminal translating tool implemented in Python
Home-page: https://github.com/veelion/tt
Author: Veelion
Author-email: veelion@gmail.com
License: MIT
Platform: UNKNOWN
